README.md
setup.py
stub_generator/__init__.py
stub_generator/__version__.py
stub_generator/stub_generator.py
stub_generator.egg-info/PKG-INFO
stub_generator.egg-info/SOURCES.txt
stub_generator.egg-info/dependency_links.txt
stub_generator.egg-info/entry_points.txt
stub_generator.egg-info/requires.txt
stub_generator.egg-info/top_level.txt