Metadata-Version: 2.1
Name: stub-generator
Version: 1.2.2
Summary: Python stub generator
Home-page: https://github.com/micheleantonazzi/python-stub-runtime-generator
Author: Michele Antonazzi
Author-email: micheleantonazzi@gmail.com
License: Apache License 2.0
Platform: UNKNOWN
Classifier: License :: OSI Approved :: Apache Software License
Classifier: Programming Language :: Python :: 3
Requires-Python: >3.6.0
Provides-Extra: test
